easyths/__init__.py
easyths/main.py
easyths/trade_client.py
easyths/api/app.py
easyths/api/dependencies/__init__.py
easyths/api/dependencies/common.py
easyths/api/middleware/__init__.py
easyths/api/middleware/api_key_auth.py
easyths/api/middleware/ip_whitelist.py
easyths/api/middleware/logging.py
easyths/api/middleware/rate_limit.py
easyths/api/routes/__init__.py
easyths/api/routes/mcp_server.py
easyths/api/routes/operations.py
easyths/api/routes/queue.py
easyths/api/routes/system.py
easyths/assets/config_example.toml
easyths/core/__init__.py
easyths/core/base_operation.py
easyths/core/operation_queue.py
easyths/core/tonghuashun_automator.py
easyths/models/__init__.py
easyths/models/operations.py
easyths/operations/buy.py
easyths/operations/condition_buy.py
easyths/operations/condition_order_cancel.py
easyths/operations/condition_order_query.py
easyths/operations/funds_query.py
easyths/operations/historical_commission_query.py
easyths/operations/holding_query.py
easyths/operations/order_cancel.py
easyths/operations/order_query.py
easyths/operations/reverse_repo_buy.py
easyths/operations/reverse_repo_query.py
easyths/operations/sell.py
easyths/operations/stop_loss_profit.py
easyths/utils/__init__.py
easyths/utils/captcha_ocr.py
easyths/utils/config.py
easyths/utils/logger.py
easyths/utils/screen_capture.py
easyths/utils/table_text_handel.py
easyths-1.5.0.dist-info/licenses/LICENSE
easyths-1.5.0.dist-info/METADATA
easyths-1.5.0.dist-info/WHEEL
easyths-1.5.0.dist-info/entry_points.txt
easyths-1.5.0.dist-info/top_level.txt
easyths-1.5.0.dist-info/RECORD
