Metadata-Version: 2.4
Name: easyths
Version: 1.5.0
Summary: 同花顺交易自动化系统
Author-email: noimank <noimank@163.com>
License-Expression: MIT
Project-URL: Homepage, https://github.com/noimank/easyths
Project-URL: Repository, https://github.com/noimank/easyths.git
Project-URL: Issues, https://github.com/noimank/easyths/issues
Keywords: trading,automation,tonghuashun,quantitative
Classifier: Programming Language :: Python :: 3
Classifier: Programming Language :: Python :: 3.12
Classifier: Programming Language :: Python :: 3.13
Classifier: Operating System :: Microsoft :: Windows
Requires-Python: <3.14,>=3.12
License-File: LICENSE
Requires-Dist: pydantic>=2.10.0
Requires-Dist: httpx>=0.28.0
Requires-Dist: numpy<2.4.0
Provides-Extra: server
Requires-Dist: fastapi>=0.115.0; extra == "server"
Requires-Dist: uvicorn[standard]>=0.32.0; extra == "server"
Requires-Dist: pydantic-settings>=2.6.0; extra == "server"
Requires-Dist: wsproto>=1.2; extra == "server"
Requires-Dist: fastmcp>=0.4.0; extra == "server"
Requires-Dist: pywinauto>=0.6.8; extra == "server"
Requires-Dist: pywin32>=308; extra == "server"
Requires-Dist: structlog>=24.4.0; extra == "server"
Requires-Dist: colorama>=0.4.6; extra == "server"
Requires-Dist: PyYAML>=6.0.2; extra == "server"
Requires-Dist: python-dotenv>=1.0.1; extra == "server"
Requires-Dist: python-multipart>=0.0.12; extra == "server"
Requires-Dist: aiofiles>=24.1.0; extra == "server"
Requires-Dist: pillow>=12.0.0; extra == "server"
Requires-Dist: pandas>=2.3.3; extra == "server"
Requires-Dist: tabulate>=0.9.0; extra == "server"
Requires-Dist: python-dateutil>=2.8.2; extra == "server"
Requires-Dist: pyperclip>=1.11.0; extra == "server"
Requires-Dist: mss>=10.1.0; extra == "server"
Requires-Dist: toml>=0.10.2; extra == "server"
Requires-Dist: ddddocr>=1.5.6; extra == "server"
Requires-Dist: psutil>=7.1.3; extra == "server"
Provides-Extra: dev
Requires-Dist: easyths[server]; extra == "dev"
Requires-Dist: black>=24.10.0; extra == "dev"
Requires-Dist: ruff>=0.8.0; extra == "dev"
Requires-Dist: mypy>=1.13.0; extra == "dev"
Requires-Dist: pre-commit>=4.0.1; extra == "dev"
Requires-Dist: mkdocs-material>=9.7.1; extra == "dev"
Requires-Dist: mkdocs-minify-plugin>=0.8.0; extra == "dev"
Dynamic: license-file
